kumc/__init__.py
kumc/auth.py
kumc/client.py
kumc/exception.py
kumc/utils.py
kumc-0.1.1.dist-info/licenses/LICENSE
kumc-0.1.1.dist-info/WHEEL
kumc-0.1.1.dist-info/METADATA
kumc-0.1.1.dist-info/RECORD
